pandas_summary/__init__.py
pandas_summary-0.2.0.dist-info/LICENSE
pandas_summary-0.2.0.dist-info/METADATA
pandas_summary-0.2.0.dist-info/WHEEL
pandas_summary-0.2.0.dist-info/top_level.txt
pandas_summary-0.2.0.dist-info/RECORD
